[{"accountKey":"84787719901","name":"Web-Enabled Matrix E-Markets and Sons","fein":"37-3771768","street":"278 Nader Grove","city":"Port Fredashire","state":"MA","zip":"05311-5742","dba":"Web-Enabled Matrix E-Markets and Sons","family_exemption":false,"medical_exemption":false,"updated_date":"2022-03-10T15:04:00-07:00","size":"small","withholdings":[3737.71,3737.71,3737.71,3737.71],"metadata":{"has_employees":true}},{"accountKey":"89815561944","name":"Mission-Critical Drive Portals Group","fein":"84-4696391","street":"768 Davis Well","city":"Lake Maryam","state":"MA","zip":"81629-0646","dba":"Mission-Critical Drive Portals Group","family_exemption":false,"medical_exemption":false,"updated_date":"2022-03-10T15:04:00-07:00","size":"small","withholdings":[8446.96,8446.96,8446.96,8446.96],"metadata":{"has_employees":true}},{"accountKey":"30521435576","name":"B2C Incentivize Users LLC","fein":"14-9589112","street":"202 Windler Spur","city":"West Lempimouth","state":"MA","zip":"03854-3647","dba":"B2C Incentivize Users LLC","family_exemption":false,"medical_exemption":false,"updated_date":"2022-03-10T15:04:00-07:00","size":"small","withholdings":[0,0,0,0],"metadata":{"register_leave_admins":true}},{"accountKey":"10205111229","name":"Dot-Com Mesh Supply-Chains Inc","fein":"11-5288886","street":"93322 Frank Flats","city":"Prosaccohaven","state":"MA","zip":"06306-6844","dba":"Dot-Com Mesh Supply-Chains Inc","family_exemption":false,"medical_exemption":false,"updated_date":"2022-03-10T15:04:00-07:00","size":"small","withholdings":[1152.88,1152.88,1152.88,1152.88],"metadata":{"register_leave_admins":true}},{"accountKey":"54278569943","name":"Innovative Engineer Initiatives LLC","fein":"79-5798904","street":"2224 Mills Trail","city":"North Dallas","state":"MA","zip":"74287-4629","dba":"Innovative Engineer Initiatives LLC","family_exemption":false,"medical_exemption":false,"updated_date":"2022-03-10T15:04:00-07:00","size":"small","withholdings":[7957.98,7957.98,7957.98,7957.98],"metadata":{"register_leave_admins":true}}]